{"name":"Enter Test","testSteps":[{"number":1,"description":"Then google is opened","duration":5274,"startTime":1482830431790,"screenshots":[{"screenshot":"d26e49164643f661a7fd67ad34b81bc2.png"}],"result":"SUCCESS","precondition":false,"children":[{"number":2,"description":"Open yandex","duration":3456,"startTime":1482830432019,"screenshots":[{"screenshot":"f75061b24706e29c4bce14f0e35efe6d.png"}],"result":"SUCCESS","precondition":false}]},{"number":3,"description":"Then user enters test","duration":1103,"startTime":1482830437064,"screenshots":[{"screenshot":"f75061b24706e29c4bce14f0e35efe6d.png"},{"screenshot":"f52a589d6165a13f491202fe2b3239a1.png"}],"result":"SUCCESS","precondition":false,"children":[{"number":4,"description":"Search: test","duration":515,"startTime":1482830437387,"screenshots":[{"screenshot":"2048a817ca950a9f04bcce52e0fb6b56.png"},{"screenshot":"fd65e638313bada9d8ef2f62db4db8f8.png"}],"result":"SUCCESS","precondition":false}]}],"userStory":{"id":"google-sample-test","storyName":"Google sample test","path":"google.feature","type":"feature"},"featureTag":{"name":"Google sample test","type":"feature"},"title":"Enter Test","description":"","backgroundTitle":"Open Google","backgroundDescription":"","tags":[{"name":"Google sample test","type":"feature"}],"startTime":1482830431684,"duration":6483,"sessionId":"cb472b6a9c49e546f1642a2b6ef4c251","driver":"chrome","manual":false,"testSource":"Cucumber","result":"SUCCESS"}